LICENSE.md
MANIFEST.in
README.md
VERSION
setup.cfg
setup.py
src/electric/__init__.py
src/electric/browser.py
src/electric/config.py
src/electric/interpolate.py
src/electric/main.py
src/electric/validators.py
src/electric/resources/__init__.py
src/electric/resources/auth.py
src/electric_data_cli.egg-info/PKG-INFO
src/electric_data_cli.egg-info/SOURCES.txt
src/electric_data_cli.egg-info/dependency_links.txt
src/electric_data_cli.egg-info/entry_points.txt
src/electric_data_cli.egg-info/not-zip-safe
src/electric_data_cli.egg-info/requires.txt
src/electric_data_cli.egg-info/top_level.txt
test/test_main.py