Metadata-Version: 2.1
Name: electric-data-cli
Version: 0.0.3
Summary: Electric Data command line interface utility.
Home-page: https://github.com/electric-data/electric-cli
Author: Electric Data
Author-email: info@electricdata.net
License: MIT
Platform: UNKNOWN
Classifier: Intended Audience :: Developers
Classifier: License :: OSI Approved :: MIT License
Classifier: Programming Language :: Python :: 3
Requires-Python: >=3.5
License-File: LICENSE.md
